soft_learn_project/CherryStudio_learn.py
soft_learn_project/GzipLearn.py
soft_learn_project/PyPDF2Learn.py
soft_learn_project/__init__.py
soft_learn_project/__main__.py
soft_learn_project/abinitLearn.py
soft_learn_project/abipyLearn.py
soft_learn_project/aimsLearn.py
soft_learn_project/ampLearn.py
soft_learn_project/anacondaLearn.py
soft_learn_project/argparseLearn.py
soft_learn_project/baderLearn.py
soft_learn_project/base64_learn.py
soft_learn_project/beautifulsoup_learn.py
soft_learn_project/binascii_learn.py
soft_learn_project/chgnetlearn.py
soft_learn_project/collectionsLearn.py
soft_learn_project/concurrent_learn.py
soft_learn_project/condaLearn.py
soft_learn_project/copyLearn.py
soft_learn_project/cp2kLearn.py
soft_learn_project/crystal_learn.py
soft_learn_project/csv_learn.py
soft_learn_project/cursorLearn.py
soft_learn_project/dataclassesLearn.py
soft_learn_project/datetimeLearn.py
soft_learn_project/deprecatedLearn.py
soft_learn_project/dpgenLearn.py
soft_learn_project/enumLearn.py
soft_learn_project/erdanticLearn.py
soft_learn_project/fabricLearn.py
soft_learn_project/functoolsLearn.py
soft_learn_project/glob_learn.py
soft_learn_project/glom_learn.py
soft_learn_project/gulpLearn.py
soft_learn_project/gym_learn.py
soft_learn_project/hanlpLearn.py
soft_learn_project/hashlib_learn.py
soft_learn_project/hatchLearn.py
soft_learn_project/hotbitLearn.py
soft_learn_project/htespLearn.py
soft_learn_project/inspectLearn.py
soft_learn_project/itertoolsLearn.py
soft_learn_project/jiebaLearn.py
soft_learn_project/jmolLearn.py
soft_learn_project/jsonLearn.py
soft_learn_project/linuxLearn.py
soft_learn_project/mambaLearn.py
soft_learn_project/matglLearn.py
soft_learn_project/math_learn.py
soft_learn_project/mayaviLearn.py
soft_learn_project/memrayLearn.py
soft_learn_project/montyLearn.py
soft_learn_project/moviepyLearn.py
soft_learn_project/mp_apiLearn.py
soft_learn_project/multiwfnLearn.py
soft_learn_project/openaiLearn.py
soft_learn_project/openmmLearn.py
soft_learn_project-0.0.2.dist-info/licenses/LICENSE
soft_learn_project-0.0.2.dist-info/METADATA
soft_learn_project-0.0.2.dist-info/WHEEL
soft_learn_project-0.0.2.dist-info/top_level.txt
soft_learn_project-0.0.2.dist-info/RECORD
