Metadata-Version: 2.4
Name: soft-learn-project
Version: 0.0.2
Author-email: wangjinlong <396292346@qq.com>
License: MIT
Requires-Python: >=3.11
License-File: LICENSE
Requires-Dist: ipykernel
Requires-Dist: ase
Requires-Dist: janus-core[all]
Requires-Dist: gpaw
Dynamic: license-file
